{"active": {"total_year": 16, "1": {"1": {"total_day": 0}, "2": {"total_day": 0}, "3": {"total_day": 0}, "4": {"total_day": 0}, "5": {"total_day": 0}, "6": {"total_day": 0}, "7": {"total_day": 0}, "8": {"total_day": 0}, "9": {"total_day": 0}, "10": {"total_day": 0}, "11": {"total_day": 0}, "12": {"total_day": 0}, "13": {"total_day": 0}, "14": {"total_day": 0}, "15": {"total_day": 0}, "16": {"total_day": 0}, "17": {"total_day": 0}, "18": {"total_day": 0}, "19": {"total_day": 0}, "20": {"total_day": 0}, "21": {"total_day": 0}, "22": {"total_day": 0}, "23": {"total_day": 0}, "24": {"total_day": 0}, "25": {"total_day": 0}, "26": {"total_day": 0}, "27": {"total_day": 0}, "28": {"total_day": 0}, "29": {"total_day": 0}, "30": {"total_day": 0}, "31": {"total_day": 0}, "total_month": 0}, "2": {"1": {"total_day": 0}, "2": {"total_day": 0}, "3": {"total_day": 0}, "4": {"total_day": 0}, "5": {"total_day": 0}, "6": {"total_day": 0}, "7": {"total_day": 0}, "8": {"total_day": 0}, "9": {"44648": {"tn": "2023020954000327", "title": "[RRD] - [CYT] - Revision de respaldos ADM CSOC [09-02-2023]", "user_id": 59, "customer_id": "VCYT", "service_id": 46, "state": "closed successful", "type": "Accion Preventiva", "ticket_priority": "3 normal", "sla": 1080, "create_time": "2023-02-09 08:01:17", "change_time": "2023-02-09 09:06:42", "resolution_time": "1:05:25"}, "44664": {"tn": "2023020954000489", "title": "Problemas con acceso PAM hcc-dev", "user_id": 12, "customer_id": "VCYT", "service_id": 46, "state": "Pendiente Cliente", "type": "Consultas", "ticket_priority": "3 normal", "sla": 1080, "create_time": "2023-02-09 09:57:11", "change_time": "2023-02-09 10:48:42", "resolution_time": "0:51:31"}, "total_day": 2}, "total_month": 2}, "2": {"1": {"total_day": 0}, "2": {"total_day": 0}, "3": {"total_day": 0}, "4": {"total_day": 0}, "5": {"total_day": 0}, "6": {"total_day": 0}, "7": {"total_day": 0}, "8": {"total_day": 0}, "9": {"total_day": 0}, "10": {"44770": {"tn": "2023021054000306", "title": "[RRD] - [CYT] - Revision de respaldos ADM CSOC [10-02-2023]", "user_id": 59, "customer_id": "VCYT", "service_id": 46, "state": "Pendiente Escalamiento", "type": "Accion Preventiva", "ticket_priority": "3 normal", "sla": 1080, "create_time": "2023-02-10 08:01:23", "change_time": "2023-02-10 08:11:36", "resolution_time": "0:10:12"}, "total_day": 1}, "total_month": 1}}, "last_ticket_id": 44770, "last_period": "2023-02-01"}